{
    "npcs": [
        {
            "id": 1,
            "name": "Michael Guerreiro",
            "initiativeModifier": 6,
            "currentHp": 12,
            "isPlayer": true,
            "active": true,
            "seuTurno": false,
            "details": {
                "id": 1,
                "movement": 9,
                "notes": "Este personagem está carregando um símbolo sagrado.",
                "armorClass": 19,
                "skill1": {
                    "id": 1,
                    "name": "Percepção",
                    "modifier": 2
                },
                "skill2": {
                    "id": 2,
                    "name": "Atletismo",
                    "modifier": 3
                },
                "skill3": {
                    "id": 3,
                    "name": "Investigação",
                    "modifier": -1
                },
                "attack1": {
                    "id": 1,
                    "weapon": "Espada longa",
                    "modifier": 5,
                    "damage": "corte 1d8+3"
                },
                "attack2": {
                    "id": 2,
                    "weapon": "Espada curta",
                    "modifier": 5,
                    "damage": "corte 1d8+3"
                },
                "attack3": {
                    "id": 3,
                    "weapon": "Arco curto",
                    "modifier": 3,
                    "damage": "corte 1d8+1"
                }
            }
        }
    ]
}